filespawn/__init__.py
filespawn/main.py
filespawn-1.0.0.dist-info/LICENSE
filespawn-1.0.0.dist-info/METADATA
filespawn-1.0.0.dist-info/WHEEL
filespawn-1.0.0.dist-info/entry_points.txt
filespawn-1.0.0.dist-info/RECORD
