Metadata-Version: 2.3
Name: filespawn
Version: 1.0.0
Summary: A simple, fast, and highly configurable command-line tool for generating dummy files.
License: MIT
Author: Ang Aik Meng
Author-email: aikmeng@hotmail.com
Requires-Python: >=3.10
Classifier: License :: OSI Approved :: MIT License
Classifier: Programming Language :: Python :: 3
Classifier: Programming Language :: Python :: 3.10
Classifier: Programming Language :: Python :: 3.11
Classifier: Programming Language :: Python :: 3.12
Classifier: Programming Language :: Python :: 3.13
Requires-Dist: click (>=8.2.1,<9.0.0)
Requires-Dist: rich (>=14.1.0,<15.0.0)
